INSTALL
LICENSE
MANIFEST.in
NEWS
README
setup.py
db/gateway.sql
db/pubsub.sql
db/to_idavoll_0.8.sql
idavoll/__init__.py
idavoll/backend.py
idavoll/error.py
idavoll/gateway.py
idavoll/iidavoll.py
idavoll/memory_storage.py
idavoll/pgsql_storage.py
idavoll/tap.py
idavoll/tap_http.py
idavoll.egg-info/PKG-INFO
idavoll.egg-info/SOURCES.txt
idavoll.egg-info/dependency_links.txt
idavoll.egg-info/not-zip-safe
idavoll.egg-info/requires.txt
idavoll.egg-info/top_level.txt
idavoll/test/__init__.py
idavoll/test/test_backend.py
idavoll/test/test_gateway.py
idavoll/test/test_storage.py
twisted/plugins/dropin.cache
twisted/plugins/idavoll.py
twisted/plugins/idavoll.pyc
twisted/plugins/idavoll_http.py
twisted/plugins/idavoll_http.pyc