Metadata-Version: 1.0
Name: idavoll
Version: 0.9.1
Summary: Jabber Publish-Subscribe Service Component
Home-page: http://idavoll.ik.nu/
Author: Ralph Meijer
Author-email: ralphm@ik.nu
License: MIT
Platform: UNKNOWN
